simple_lm/__init__.py
simple_lm/core.py
simple_lm-0.1.3.dist-info/METADATA
simple_lm-0.1.3.dist-info/WHEEL
simple_lm-0.1.3.dist-info/RECORD
