Metadata-Version: 2.1
Name: simple-lm
Version: 0.1.3
Summary: A simple abstraction over instructor for LLM apps
License: MIT
Author: Joe Petrantoni
Author-email: 79169021+jpetrantoni@users.noreply.github.com
Requires-Python: >=3.10,<4.0
Classifier: License :: OSI Approved :: MIT License
Classifier: Programming Language :: Python :: 3
Classifier: Programming Language :: Python :: 3.10
Classifier: Programming Language :: Python :: 3.11
Classifier: Programming Language :: Python :: 3.12
Requires-Dist: anthropic (>=0.23.1,<0.24.0)
Requires-Dist: instructor (>=1.2.1,<2.0.0)
Requires-Dist: openai (>=1.21.2,<2.0.0)
